COPYING.md
MANIFEST.in
README.md
setup.py
djungle/__init__.py
djungle/underscore/__init__.py
djungle/underscore/static/djungle/underscore.full.js
djungle/underscore/static/djungle/underscore.js
djungle_underscore.egg-info/PKG-INFO
djungle_underscore.egg-info/SOURCES.txt
djungle_underscore.egg-info/dependency_links.txt
djungle_underscore.egg-info/namespace_packages.txt
djungle_underscore.egg-info/not-zip-safe
djungle_underscore.egg-info/requires.txt
djungle_underscore.egg-info/top_level.txt