Metadata-Version: 1.0
Name: djungle-underscore
Version: 0.0.1
Summary: Underscore.js as Django app.
Home-page: https://github.com/djungle/djungle-underscore
Author: Hendrik M Halkow
Author-email: hendrik@halkow.com
License: UNKNOWN
Platform: UNKNOWN
Classifier: Development Status :: 1 - Planning
Classifier: Environment :: Web Environment
Classifier: Framework :: Django
Classifier: Intended Audience :: Developers
Classifier: License :: OSI Approved :: GNU General Public License (GPL)
Classifier: Operating System :: OS Independent
Classifier: Programming Language :: Python
Classifier: Topic :: Internet :: WWW/HTTP
Classifier: Topic :: Software Development :: User Interfaces
Classifier: Topic :: Text Processing :: Markup :: HTML
